MANIFEST.in
README.rst
setup.py
webassets_recess/__init__.py
webassets_recess.egg-info/PKG-INFO
webassets_recess.egg-info/SOURCES.txt
webassets_recess.egg-info/dependency_links.txt
webassets_recess.egg-info/not-zip-safe
webassets_recess.egg-info/top_level.txt