Metadata-Version: 1.1
Name: webassets-recess
Version: 0.0.0
Summary: Recess filter to compile less with webassets, enables twitter bootstrap less compiling
Home-page: http://github.com/yourlabs/webassets-recess
Author: James Pic
Author-email: jamespic@gmail.com
License: MIT
Keywords: lesscss recess webassets
Platform: UNKNOWN
Classifier: Development Status :: 3 - Alpha
Classifier: Intended Audience :: Developers
Classifier: License :: OSI Approved :: MIT License
Classifier: Operating System :: OS Independent
Classifier: Programming Language :: Python
Classifier: Programming Language :: Python :: 2
Classifier: Topic :: Software Development :: Libraries :: Python Modules
